AUTHORS.rst
CHANGES.rst
COPYING
LICENSE
MANIFEST.in
README.rst
setup.py
GeophPy.egg-info/PKG-INFO
GeophPy.egg-info/SOURCES.txt
GeophPy.egg-info/dependency_links.txt
GeophPy.egg-info/not-zip-safe
GeophPy.egg-info/requires.txt
GeophPy.egg-info/top_level.txt
docs/.gitignore
docs/Makefile
docs/about.rst
docs/api.rst
docs/changes.rst
docs/conf.py
docs/feedback.rst
docs/gen-proc.rst
docs/geopos.rst
docs/gui.rst
docs/index.rst
docs/install.rst
docs/mag-proc.rst
docs/make.bat
docs/plot-fun.rst
docs/quick-start.rst
docs/references.rst
docs/_build/doctrees/about.doctree
docs/_build/doctrees/api.doctree
docs/_build/doctrees/changes.doctree
docs/_build/doctrees/environment.pickle
docs/_build/doctrees/feedback.doctree
docs/_build/doctrees/gen-proc.doctree
docs/_build/doctrees/geopos.doctree
docs/_build/doctrees/gui.doctree
docs/_build/doctrees/index.doctree
docs/_build/doctrees/install.doctree
docs/_build/doctrees/mag-proc.doctree
docs/_build/doctrees/plot-fun.doctree
docs/_build/doctrees/quick-start.doctree
docs/_build/doctrees/references.doctree
docs/_build/html/.buildinfo
docs/_build/html/about.html
docs/_build/html/api.html
docs/_build/html/changes.html
docs/_build/html/feedback.html
docs/_build/html/gen-proc.html
docs/_build/html/genindex.html
docs/_build/html/geopos.html
docs/_build/html/gui.html
docs/_build/html/index.html
docs/_build/html/install.html
docs/_build/html/mag-proc.html
docs/_build/html/objects.inv
docs/_build/html/plot-fun.html
docs/_build/html/py-modindex.html
docs/_build/html/quick-start.html
docs/_build/html/references.html
docs/_build/html/search.html
docs/_build/html/searchindex.js
docs/_build/html/_images/figAlgoAnalyticSignal.png
docs/_build/html/_images/figAlgoContinuation.png
docs/_build/html/_images/figAlgoPoleReduction.png
docs/_build/html/_images/figAnglesRepresentation.png
docs/_build/html/_images/figApodisation.png
docs/_build/html/_images/figCarto2.png
docs/_build/html/_images/figCarto4.png
docs/_build/html/_images/figCarto5.png
docs/_build/html/_images/figCorrelationMap.png
docs/_build/html/_images/figCorrelationSum.png
docs/_build/html/_images/figDestriping1.png
docs/_build/html/_images/figDestriping2.png
