Metadata-Version: 2.1
Name: GeophPy
Version: 0.32.2
Summary: Tools for sub-surface geophysical survey data processing
Home-page: UNKNOWN
Author: Lionel Darras, Philippe Marty & Quentin Vitale
Author-email: lionel.darras@mom.fr
Maintainer: Lionel Darras, Philippe Marty & Quentin Vitale
Maintainer-email: lionel.darras@mom.fr
License: GNU GPL v3
Platform: UNKNOWN
Classifier: Development Status :: 4 - Beta
Classifier: Intended Audience :: Developers
Classifier: Intended Audience :: Science/Research
Classifier: License :: OSI Approved :: GNU General Public License v3 (GPLv3)
Classifier: Programming Language :: Python :: 3.4
Classifier: Programming Language :: Python :: 3.5
Classifier: Programming Language :: Python :: 3.6
Classifier: Programming Language :: Python :: 3.7
Classifier: Topic :: Scientific/Engineering
Classifier: Topic :: Scientific/Engineering :: Physics
Classifier: Topic :: Utilities
Classifier: Topic :: Software Development :: Libraries :: Python Modules
License-File: LICENSE
License-File: COPYING
License-File: AUTHORS.rst
